{"@timestamp":"1717782188862","@index":0,"@class":"android.widget.FrameLayout","@package":"com.pingan.papd","@checkable":false,"@checked":false,"@clickable":false,"@enabled":true,"@focusable":false,"@focused":false,"@scrollable":false,"@long-clickable":false,"@selected":false,"@editable":false,"@bounds":"[0,0][1080,2310]","@screenBounds":"[0,0][0,0]","node":{"@timestamp":"1717782188862","@index":0,"@class":"android.widget.LinearLayout","@package":"com.pingan.papd","@checkable":false,"@checked":false,"@clickable":false,"@enabled":true,"@focusable":false,"@focused":false,"@scrollable":false,"@long-clickable":false,"@selected":false,"@editable":false,"@bounds":"[0,0][1080,2192]","@screenBounds":"[0,0][0,0]","node":{"@timestamp":"1717782188862","@index":0,"@class":"android.widget.FrameLayout","@package":"com.pingan.papd","@checkable":false,"@checked":false,"@clickable":false,"@enabled":true,"@focusable":false,"@focused":false,"@scrollable":false,"@long-clickable":false,"@selected":false,"@editable":false,"@bounds":"[0,117][1080,2192]","@screenBounds":"[0,0][0,0]","node":{"@timestamp":"1717782188863","@index":0,"@resource-id":"com.pingan.papd:id\/decor_content_parent","@class":"android.view.ViewGroup","@package":"com.pingan.papd","@checkable":false,"@checked":false,"@clickable":false,"@enabled":true,"@focusable":false,"@focused":false,"@scrollable":false,"@long-clickable":false,"@selected":false,"@editable":false,"@bounds":"[0,117][1080,2192]","@screenBounds":"[0,0][0,0]","node":{"@timestamp":"1717782188863","@index":0,"@resource-id":"android:id\/content","@class":"android.widget.FrameLayout","@package":"com.pingan.papd","@checkable":false,"@checked":false,"@clickable":false,"@enabled":true,"@focusable":false,"@focused":false,"@scrollable":false,"@long-clickable":false,"@selected":false,"@editable":false,"@bounds":"[0,117][1080,2192]","@screenBounds":"[0,0][0,0]","node":{"@timestamp":"1717782188863","@index":0,"@class":"android.widget.LinearLayout","@package":"com.pingan.papd","@checkable":false,"@checked":false,"@clickable":false,"@enabled":true,"@focusable":false,"@focused":false,"@scrollable":false,"@long-clickable":false,"@selected":false,"@editable":false,"@bounds":"[0,117][1080,2192]","@screenBounds":"[0,0][0,0]","node":{"@timestamp":"1717782188863","@index":0,"@class":"android.widget.FrameLayout","@package":"com.pingan.papd","@checkable":false,"@checked":false,"@clickable":false,"@enabled":true,"@focusable":false,"@focused":false,"@scrollable":false,"@long-clickable":false,"@selected":false,"@editable":false,"@bounds":"[0,117][1080,2192]","@screenBounds":"[0,0][0,0]","node":[{"@timestamp":"1717782188863","@index":0,"@resource-id":"com.pingan.papd:id\/ll_content_new","@class":"android.widget.LinearLayout","@package":"com.pingan.papd","@checkable":false,"@checked":false,"@clickable":false,"@enabled":true,"@focusable":false,"@focused":false,"@scrollable":false,"@long-clickable":false,"@selected":false,"@editable":false,"@bounds":"[0,117][1080,2192]","@screenBounds":"[0,0][0,0]","node":{"@timestamp":"1717782188863","@index":0,"@class":"android.widget.FrameLayout","@package":"com.pingan.papd","@checkable":false,"@checked":false,"@clickable":false,"@enabled":true,"@focusable":false,"@focused":false,"@scrollable":false,"@long-clickable":false,"@selected":false,"@editable":false,"@bounds":"[0,117][1080,2192]","@screenBounds":"[0,0][0,0]","node":{"@timestamp":"1717782188863","@index":0,"@class":"android.webkit.WebView","@package":"com.pingan.papd","@checkable":false,"@checked":false,"@clickable":false,"@enabled":true,"@focusable":false,"@focused":false,"@scrollable":false,"@long-clickable":false,"@selected":false,"@editable":false,"@bounds":"[0,117][1080,2192]","@screenBounds":"[0,0][0,0]","node":{"@timestamp":"1717782188863","@index":0,"@text":"平安健康","@class":"android.webkit.WebView","@package":"com.pingan.papd","@checkable":false,"@checked":false,"@clickable":false,"@enabled":true,"@focusable":true,"@focused":true,"@scrollable":false,"@long-clickable":false,"@selected":false,"@editable":false,"@bounds":"[0,117][1080,2193]","@screenBounds":"[0,0][0,0]","node":{"@timestamp":"1717782188864","@index":0,"@text":"","@resource-id":"root","@class":"android.view.View","@package":"com.pingan.papd","@checkable":false,"@checked":false,"@clickable":false,"@enabled":true,"@focusable":false,"@focused":false,"@scrollable":false,"@long-clickable":false,"@selected":false,"@editable":false,"@bounds":"[0,117][1080,2193]","@screenBounds":"[0,0][0,0]","node":{"@timestamp":"1717782188864","@index":0,"@text":"","@class":"android.view.View","@package":"com.pingan.papd","@checkable":false,"@checked":false,"@clickable":false,"@enabled":true,"@focusable":false,"@focused":false,"@scrollable":false,"@long-clickable":false,"@selected":false,"@editable":false,"@bounds":"[0,117][1080,2193]","@screenBounds":"[0,0][0,0]","node":{"@timestamp":"1717782188864","@index":0,"@text":"","@resource-id":"my-consult-page","@class":"android.view.View","@package":"com.pingan.papd","@checkable":false,"@checked":false,"@clickable":false,"@enabled":true,"@focusable":false,"@focused":false,"@scrollable":false,"@long-clickable":false,"@selected":false,"@editable":false,"@bounds":"[0,117][1080,2193]","@screenBounds":"[0,0][0,0]","node":{"@timestamp":"1717782188864","@index":0,"@text":"","@class":"android.view.View","@package":"com.pingan.papd","@checkable":false,"@checked":false,"@clickable":false,"@enabled":true,"@focusable":false,"@focused":false,"@scrollable":false,"@long-clickable":false,"@selected":false,"@editable":false,"@bounds":"[0,117][1080,2193]","@screenBounds":"[0,0][0,0]","node":[{"@timestamp":"1717782188864","@index":0,"@text":"","@resource-id":"medicine-record-header","@class":"android.view.View","@package":"com.pingan.papd","@checkable":false,"@checked":false,"@clickable":false,"@enabled":true,"@focusable":false,"@focused":false,"@scrollable":false,"@long-clickable":false,"@selected":false,"@editable":false,"@bounds":"[0,117][1080,372]","@screenBounds":"[0,0][0,0]","node":[{"@timestamp":"1717782188864","@index":0,"@text":"","@class":"android.view.View","@package":"com.pingan.papd","@checkable":false,"@checked":false,"@clickable":false,"@enabled":true,"@focusable":false,"@focused":false,"@scrollable":false,"@long-clickable":false,"@selected":false,"@editable":false,"@bounds":"[0,117][1080,246]","@screenBounds":"[0,0][0,0]","node":{"@timestamp":"1717782188864","@index":0,"@text":"我的问诊","@class":"android.widget.TextView","@package":"com.pingan.papd","@checkable":false,"@checked":false,"@clickable":false,"@enabled":true,"@focusable":false,"@focused":false,"@scrollable":false,"@long-clickable":false,"@selected":false,"@editable":false,"@bounds":"[162,117][918,246]","@screenBounds":"[0,0][0,0]"}},{"@timestamp":"1717782188864","@index":1,"@text":"","@class":"android.view.View","@package":"com.pingan.papd","@checkable":false,"@checked":false,"@clickable":false,"@enabled":true,"@focusable":false,"@focused":false,"@scrollable":true,"@long-clickable":false,"@selected":false,"@editable":false,"@bounds":"[0,243][1080,372]","@screenBounds":"[0,0][0,0]","node":[{"@timestamp":"1717782188865","@index":0,"@text":"","@class":"android.view.View","@package":"com.pingan.papd","@checkable":false,"@checked":false,"@clickable":true,"@enabled":true,"@focusable":false,"@focused":false,"@scrollable":false,"@long-clickable":false,"@selected":false,"@editable":false,"@bounds":"[0,243][273,372]","@screenBounds":"[0,0][0,0]","node":{"@timestamp":"1717782188865","@index":0,"@text":"问诊记录","@class":"android.widget.TextView","@package":"com.pingan.papd","@checkable":false,"@checked":false,"@clickable":false,"@enabled":true,"@focusable":false,"@focused":false,"@scrollable":false,"@long-clickable":false,"@selected":false,"@editable":false,"@bounds":"[42,243][228,372]","@screenBounds":"[0,0][0,0]"}},{"@timestamp":"1717782188865","@index":1,"@text":"","@class":"android.view.View","@package":"com.pingan.papd","@checkable":false,"@checked":false,"@clickable":true,"@enabled":true,"@focusable":false,"@focused":false,"@scrollable":false,"@long-clickable":false,"@selected":false,"@editable":false,"@bounds":"[270,243][726,372]","@screenBounds":"[0,0][0,0]","node":{"@timestamp":"1717782188865","@index":0,"@text":"签约医生问诊记录","@class":"android.widget.TextView","@package":"com.pingan.papd","@checkable":false,"@checked":false,"@clickable":false,"@enabled":true,"@focusable":false,"@focused":false,"@scrollable":false,"@long-clickable":false,"@selected":false,"@editable":false,"@bounds":"[312,243][684,372]","@screenBounds":"[0,0][0,0]"}},{"@timestamp":"1717782188865","@index":2,"@text":"","@class":"android.view.View","@package":"com.pingan.papd","@checkable":false,"@checked":false,"@clickable":true,"@enabled":true,"@focusable":false,"@focused":false,"@scrollable":false,"@long-clickable":false,"@selected":false,"@editable":false,"@bounds":"[723,243][999,372]","@screenBounds":"[0,0][0,0]","node":{"@timestamp":"1717782188865","@index":0,"@text":"用药记录","@class":"android.widget.TextView","@package":"com.pingan.papd","@checkable":false,"@checked":false,"@clickable":false,"@enabled":true,"@focusable":false,"@focused":false,"@scrollable":false,"@long-clickable":false,"@selected":false,"@editable":false,"@bounds":"[768,243][954,372]","@screenBounds":"[0,0][0,0]"}},{"@timestamp":"1717782188865","@index":3,"@text":"","@class":"android.view.View","@package":"com.pingan.papd","@checkable":false,"@checked":false,"@clickable":true,"@enabled":true,"@focusable":false,"@focused":false,"@scrollable":false,"@long-clickable":false,"@selected":false,"@editable":false,"@bounds":"[996,243][1269,372]","@screenBounds":"[0,0][0,0]","node":{"@timestamp":"1717782188865","@index":0,"@text":"诊中服务","@class":"android.widget.TextView","@package":"com.pingan.papd","@checkable":false,"@checked":false,"@clickable":false,"@enabled":true,"@focusable":false,"@focused":false,"@scrollable":false,"@long-clickable":false,"@selected":false,"@editable":false,"@bounds":"[1038,243][1224,372]","@screenBounds":"[0,0][0,0]"}}]}]},{"@timestamp":"1717782188865","@index":1,"@text":"","@resource-id":"drawer","@class":"android.view.View","@package":"com.pingan.papd","@checkable":false,"@checked":false,"@clickable":false,"@enabled":true,"@focusable":false,"@focused":false,"@scrollable":false,"@long-clickable":false,"@selected":false,"@editable":false,"@bounds":"[0,369][1080,486]","@screenBounds":"[0,0][0,0]","node":[{"@timestamp":"1717782188866","@index":0,"@text":"","@class":"android.view.View","@package":"com.pingan.papd","@checkable":false,"@checked":false,"@clickable":true,"@enabled":true,"@focusable":false,"@focused":false,"@scrollable":false,"@long-clickable":false,"@selected":false,"@editable":false,"@bounds":"[45,402][540,453]","@screenBounds":"[0,0][0,0]","node":{"@timestamp":"1717782188866","@index":0,"@text":"全部就诊人","@class":"android.widget.TextView","@package":"com.pingan.papd","@checkable":false,"@checked":false,"@clickable":false,"@enabled":true,"@focusable":false,"@focused":false,"@scrollable":false,"@long-clickable":false,"@selected":false,"@editable":false,"@bounds":"[168,402][372,453]","@screenBounds":"[0,0][0,0]"}},{"@timestamp":"1717782188866","@index":1,"@text":"","@class":"android.view.View","@package":"com.pingan.papd","@checkable":false,"@checked":false,"@clickable":true,"@enabled":true,"@focusable":false,"@focused":false,"@scrollable":false,"@long-clickable":false,"@selected":false,"@editable":false,"@bounds":"[540,402][1035,453]","@screenBounds":"[0,0][0,0]","node":{"@timestamp":"1717782188866","@index":0,"@text":"全部问诊状态","@class":"android.widget.TextView","@package":"com.pingan.papd","@checkable":false,"@checked":false,"@clickable":false,"@enabled":true,"@focusable":false,"@focused":false,"@scrollable":false,"@long-clickable":false,"@selected":false,"@editable":false,"@bounds":"[642,402][885,453]","@screenBounds":"[0,0][0,0]"}}]},{"@timestamp":"1717782188866","@index":2,"@text":"","@resource-id":"page-body","@class":"android.view.View","@package":"com.pingan.papd","@checkable":false,"@checked":false,"@clickable":false,"@enabled":true,"@focusable":false,"@focused":false,"@scrollable":false,"@long-clickable":false,"@selected":false,"@editable":false,"@bounds":"[0,483][1080,2193]","@screenBounds":"[0,0][0,0]","node":{"@timestamp":"1717782188866","@index":0,"@text":"您目前还没有问诊记录哦","@class":"android.widget.TextView","@package":"com.pingan.papd","@checkable":false,"@checked":false,"@clickable":false,"@enabled":true,"@focusable":false,"@focused":false,"@scrollable":false,"@long-clickable":false,"@selected":false,"@editable":false,"@bounds":"[318,1305][762,1347]","@screenBounds":"[0,0][0,0]"}}]}}}}}}}},{"@timestamp":"1717782188866","@index":1,"@resource-id":"com.pingan.papd:id\/native_title_bar_iv_left","@class":"android.widget.ImageView","@package":"com.pingan.papd","@checkable":false,"@checked":false,"@clickable":true,"@enabled":true,"@focusable":true,"@focused":false,"@scrollable":false,"@long-clickable":false,"@selected":false,"@editable":false,"@bounds":"[0,117][132,267]","@screenBounds":"[0,0][0,0]"}]}}}}}}}