{"@timestamp":"1717762278613","@index":0,"@class":"android.widget.FrameLayout","@package":"com.ss.android.ugc.aweme","@checkable":false,"@checked":false,"@clickable":false,"@enabled":true,"@focusable":false,"@focused":false,"@scrollable":false,"@long-clickable":false,"@selected":false,"@editable":false,"@bounds":"[0,0][1080,2310]","@screenBounds":"[0,0][0,0]","node":{"@timestamp":"1717762278614","@index":0,"@class":"android.widget.FrameLayout","@package":"com.ss.android.ugc.aweme","@checkable":false,"@checked":false,"@clickable":false,"@enabled":true,"@focusable":false,"@focused":false,"@scrollable":false,"@long-clickable":false,"@selected":false,"@editable":false,"@bounds":"[0,0][1080,2310]","@screenBounds":"[0,0][0,0]","node":{"@timestamp":"1717762278614","@index":0,"@class":"android.widget.LinearLayout","@package":"com.ss.android.ugc.aweme","@checkable":false,"@checked":false,"@clickable":false,"@enabled":true,"@focusable":false,"@focused":false,"@scrollable":false,"@long-clickable":false,"@selected":false,"@editable":false,"@bounds":"[0,0][1080,2192]","@screenBounds":"[0,0][0,0]","node":{"@timestamp":"1717762278614","@index":0,"@class":"android.widget.FrameLayout","@package":"com.ss.android.ugc.aweme","@checkable":false,"@checked":false,"@clickable":false,"@enabled":true,"@focusable":false,"@focused":false,"@scrollable":false,"@long-clickable":false,"@selected":false,"@editable":false,"@bounds":"[0,0][1080,2192]","@screenBounds":"[0,0][0,0]","node":{"@timestamp":"1717762278614","@index":0,"@resource-id":"com.ss.android.ugc.aweme:id\/action_bar_root","@class":"android.widget.LinearLayout","@package":"com.ss.android.ugc.aweme","@checkable":false,"@checked":false,"@clickable":false,"@enabled":true,"@focusable":false,"@focused":false,"@scrollable":false,"@long-clickable":false,"@selected":false,"@editable":false,"@bounds":"[0,0][1080,2192]","@screenBounds":"[0,0][0,0]","node":{"@timestamp":"1717762278615","@index":0,"@class":"android.widget.FrameLayout","@package":"com.ss.android.ugc.aweme","@checkable":false,"@checked":false,"@clickable":false,"@enabled":true,"@focusable":false,"@focused":false,"@scrollable":false,"@long-clickable":false,"@selected":false,"@editable":false,"@bounds":"[0,0][1080,2192]","@screenBounds":"[0,0][0,0]","node":{"@timestamp":"1717762278615","@index":0,"@resource-id":"android:id\/content","@class":"android.widget.FrameLayout","@package":"com.ss.android.ugc.aweme","@checkable":false,"@checked":false,"@clickable":false,"@enabled":true,"@focusable":false,"@focused":false,"@scrollable":false,"@long-clickable":false,"@selected":false,"@editable":false,"@bounds":"[0,0][1080,2192]","@screenBounds":"[0,0][0,0]","node":{"@timestamp":"1717762278615","@index":0,"@resource-id":"com.ss.android.ugc.aweme.cjplugin:id\/root_linearLayout","@class":"android.widget.RelativeLayout","@package":"com.ss.android.ugc.aweme","@checkable":false,"@checked":false,"@clickable":false,"@enabled":true,"@focusable":false,"@focused":false,"@scrollable":false,"@long-clickable":false,"@selected":false,"@editable":false,"@bounds":"[0,0][1080,2192]","@screenBounds":"[0,0][0,0]","node":{"@timestamp":"1717762278615","@index":0,"@resource-id":"com.ss.android.ugc.aweme.cjplugin:id\/base_main_content","@class":"android.widget.FrameLayout","@package":"com.ss.android.ugc.aweme","@checkable":false,"@checked":false,"@clickable":false,"@enabled":true,"@focusable":false,"@focused":false,"@scrollable":false,"@long-clickable":false,"@selected":false,"@editable":false,"@bounds":"[0,0][1080,2192]","@screenBounds":"[0,0][0,0]","node":{"@timestamp":"1717762278615","@index":0,"@resource-id":"com.ss.android.ugc.aweme.cjplugin:id\/cj_pay_h5_root_view","@class":"android.widget.FrameLayout","@package":"com.ss.android.ugc.aweme","@checkable":false,"@checked":false,"@clickable":false,"@enabled":true,"@focusable":false,"@focused":false,"@scrollable":false,"@long-clickable":false,"@selected":false,"@editable":false,"@bounds":"[0,0][1080,2192]","@screenBounds":"[0,0][0,0]","node":{"@timestamp":"1717762278615","@index":0,"@resource-id":"com.ss.android.ugc.aweme.cjplugin:id\/cj_pay_webview_layout","@class":"android.widget.RelativeLayout","@package":"com.ss.android.ugc.aweme","@checkable":false,"@checked":false,"@clickable":false,"@enabled":true,"@focusable":false,"@focused":false,"@scrollable":false,"@long-clickable":false,"@selected":false,"@editable":false,"@bounds":"[0,0][1080,2192]","@screenBounds":"[0,0][0,0]","node":{"@timestamp":"1717762278615","@index":0,"@resource-id":"com.ss.android.ugc.aweme.cjplugin:id\/cj_pay_webview","@class":"android.widget.FrameLayout","@package":"com.ss.android.ugc.aweme","@checkable":false,"@checked":false,"@clickable":false,"@enabled":true,"@focusable":false,"@focused":false,"@scrollable":false,"@long-clickable":false,"@selected":false,"@editable":false,"@bounds":"[0,0][1080,2192]","@screenBounds":"[0,0][0,0]","node":{"@timestamp":"1717762278616","@index":0,"@class":"android.webkit.WebView","@package":"com.ss.android.ugc.aweme","@checkable":false,"@checked":false,"@clickable":false,"@enabled":true,"@focusable":false,"@focused":false,"@scrollable":false,"@long-clickable":false,"@selected":false,"@editable":false,"@bounds":"[0,0][1080,2192]","@screenBounds":"[0,0][0,0]","node":{"@timestamp":"1717762278616","@index":0,"@text":"关闭抖音月付","@class":"android.webkit.WebView","@package":"com.ss.android.ugc.aweme","@checkable":false,"@checked":false,"@clickable":false,"@enabled":true,"@focusable":true,"@focused":true,"@scrollable":true,"@long-clickable":false,"@selected":false,"@editable":false,"@bounds":"[0,0][1080,2192]","@screenBounds":"[0,0][0,0]","node":{"@timestamp":"1717762278616","@index":0,"@text":"","@resource-id":"__next","@class":"android.view.View","@package":"com.ss.android.ugc.aweme","@checkable":false,"@checked":false,"@clickable":false,"@enabled":true,"@focusable":false,"@focused":false,"@scrollable":false,"@long-clickable":false,"@selected":false,"@editable":false,"@bounds":"[0,0][1080,2192]","@screenBounds":"[0,0][0,0]","node":{"@timestamp":"1717762278616","@index":0,"@text":"","@class":"android.view.View","@package":"com.ss.android.ugc.aweme","@checkable":false,"@checked":false,"@clickable":false,"@enabled":true,"@focusable":false,"@focused":false,"@scrollable":false,"@long-clickable":false,"@selected":false,"@editable":false,"@bounds":"[0,0][1080,2192]","@screenBounds":"[0,0][0,0]","node":{"@timestamp":"1717762278616","@index":0,"@text":"","@resource-id":"JS_PageScroller","@class":"android.view.View","@package":"com.ss.android.ugc.aweme","@checkable":false,"@checked":false,"@clickable":false,"@enabled":true,"@focusable":false,"@focused":false,"@scrollable":true,"@long-clickable":false,"@selected":false,"@editable":false,"@bounds":"[0,0][1080,2192]","@screenBounds":"[0,0][0,0]","node":[{"@timestamp":"1717762278616","@index":0,"@text":"","@class":"android.view.View","@package":"com.ss.android.ugc.aweme","@checkable":false,"@checked":false,"@clickable":false,"@enabled":true,"@focusable":false,"@focused":false,"@scrollable":false,"@long-clickable":false,"@selected":false,"@editable":false,"@bounds":"[0,108][1080,237]","@screenBounds":"[0,0][0,0]","node":[{"@timestamp":"1717762278617","@index":0,"@text":"","@class":"android.view.View","@package":"com.ss.android.ugc.aweme","@checkable":false,"@checked":false,"@clickable":true,"@enabled":true,"@focusable":false,"@focused":false,"@scrollable":false,"@long-clickable":false,"@selected":false,"@editable":false,"@bounds":"[42,132][261,213]","@screenBounds":"[0,0][0,0]","node":{"@timestamp":"1717762278617","@index":0,"@text":"","@class":"android.widget.Button","@package":"com.ss.android.ugc.aweme","@checkable":false,"@checked":false,"@clickable":true,"@enabled":true,"@focusable":false,"@focused":false,"@scrollable":false,"@long-clickable":false,"@selected":false,"@editable":false,"@bounds":"[42,135][114,210]","@screenBounds":"[0,0][0,0]"}},{"@timestamp":"1717762278617","@index":1,"@text":"关闭抖音月付","@class":"android.view.View","@package":"com.ss.android.ugc.aweme","@checkable":false,"@checked":false,"@clickable":false,"@enabled":true,"@focusable":false,"@focused":false,"@scrollable":false,"@long-clickable":false,"@selected":false,"@editable":false,"@bounds":"[258,132][822,213]","@screenBounds":"[0,0][0,0]"},{"@timestamp":"1717762278617","@index":2,"@text":"","@class":"android.view.View","@package":"com.ss.android.ugc.aweme","@checkable":false,"@checked":false,"@clickable":false,"@enabled":true,"@focusable":false,"@focused":false,"@scrollable":false,"@long-clickable":false,"@selected":false,"@editable":false,"@bounds":"[819,132][1038,213]","@screenBounds":"[0,0][0,0]","node":[{"@timestamp":"1717762278617","@index":0,"@text":"","@class":"android.view.View","@package":"com.ss.android.ugc.aweme","@checkable":false,"@checked":false,"@clickable":true,"@enabled":true,"@focusable":false,"@focused":false,"@scrollable":false,"@long-clickable":false,"@selected":false,"@editable":false,"@bounds":"[1035,174][1254,258]","@screenBounds":"[0,0][0,0]"},{"@timestamp":"1717762278617","@index":1,"@text":"","@class":"android.view.View","@package":"com.ss.android.ugc.aweme","@checkable":false,"@checked":false,"@clickable":true,"@enabled":true,"@focusable":false,"@focused":false,"@scrollable":false,"@long-clickable":false,"@selected":false,"@editable":false,"@bounds":"[1035,174][1254,258]","@screenBounds":"[0,0][0,0]"}]}]},{"@timestamp":"1717762278617","@index":1,"@text":"retain-header-new-e9feea7900bf07ea9bc07f3a77a89908","@class":"android.widget.Image","@package":"com.ss.android.ugc.aweme","@checkable":false,"@checked":false,"@clickable":false,"@enabled":true,"@focusable":false,"@focused":false,"@scrollable":false,"@long-clickable":false,"@selected":false,"@editable":false,"@bounds":"[0,0][1080,864]","@screenBounds":"[0,0][0,0]"},{"@timestamp":"1717762278618","@index":2,"@text":"","@class":"android.view.View","@package":"com.ss.android.ugc.aweme","@checkable":false,"@checked":false,"@clickable":false,"@enabled":true,"@focusable":false,"@focused":false,"@scrollable":false,"@long-clickable":false,"@selected":false,"@editable":false,"@bounds":"[99,1299][981,1476]","@screenBounds":"[0,0][0,0]","node":{"@timestamp":"1717762278618","@index":0,"@text":"","@class":"android.view.View","@package":"com.ss.android.ugc.aweme","@checkable":false,"@checked":false,"@clickable":true,"@enabled":true,"@focusable":false,"@focused":false,"@scrollable":false,"@long-clickable":false,"@selected":false,"@editable":false,"@bounds":"[99,1299][981,1476]","@screenBounds":"[0,0][0,0]","node":[{"@timestamp":"1717762278618","@index":0,"@text":"额度将注销","@class":"android.view.View","@package":"com.ss.android.ugc.aweme","@checkable":false,"@checked":false,"@clickable":false,"@enabled":true,"@focusable":false,"@focused":false,"@scrollable":false,"@long-clickable":false,"@selected":false,"@editable":false,"@bounds":"[99,1359][717,1419]","@screenBounds":"[0,0][0,0]"},{"@timestamp":"1717762278618","@index":1,"@text":"总额度100元","@class":"android.view.View","@package":"com.ss.android.ugc.aweme","@checkable":false,"@checked":false,"@clickable":false,"@enabled":true,"@focusable":false,"@focused":false,"@scrollable":false,"@long-clickable":false,"@selected":false,"@editable":false,"@bounds":"[714,1365][945,1410]","@screenBounds":"[0,0][0,0]"},{"@timestamp":"1717762278618","@index":2,"@text":"u6qqoOqIG31rpZG10WIoWyEQm0C0mFdiMp0CHIFnQYsgblhPFnOef8IkcvyEt8csUYp8OR5biMMS3808UXf8LFw1h8rRRfkMVXvRSAjJxIAYCrFOG7MrzW+pn6kTilPrEsh2P6wvuZAAAAAElFTkSuQmCC","@class":"android.widget.Image","@package":"com.ss.android.ugc.aweme","@checkable":false,"@checked":false,"@clickable":false,"@enabled":true,"@focusable":false,"@focused":false,"@scrollable":false,"@long-clickable":false,"@selected":false,"@editable":false,"@bounds":"[942,1368][981,1407]","@screenBounds":"[0,0][0,0]"}]}},{"@timestamp":"1717762278618","@index":3,"@text":"","@class":"android.view.View","@package":"com.ss.android.ugc.aweme","@checkable":false,"@checked":false,"@clickable":true,"@enabled":true,"@focusable":false,"@focused":false,"@scrollable":false,"@long-clickable":false,"@selected":false,"@editable":false,"@bounds":"[99,1473][981,1647]","@screenBounds":"[0,0][0,0]","node":[{"@timestamp":"1717762278618","@index":0,"@text":"记录将清空","@class":"android.view.View","@package":"com.ss.android.ugc.aweme","@checkable":false,"@checked":false,"@clickable":false,"@enabled":true,"@focusable":false,"@focused":false,"@scrollable":false,"@long-clickable":false,"@selected":false,"@editable":false,"@bounds":"[99,1530][579,1590]","@screenBounds":"[0,0][0,0]"},{"@timestamp":"1717762278618","@index":1,"@text":"已使用4天，消费0笔","@class":"android.view.View","@package":"com.ss.android.ugc.aweme","@checkable":false,"@checked":false,"@clickable":false,"@enabled":true,"@focusable":false,"@focused":false,"@scrollable":false,"@long-clickable":false,"@selected":false,"@editable":false,"@bounds":"[576,1536][945,1584]","@screenBounds":"[0,0][0,0]"},{"@timestamp":"1717762278618","@index":2,"@text":"u6qqoOqIG31rpZG10WIoWyEQm0C0mFdiMp0CHIFnQYsgblhPFnOef8IkcvyEt8csUYp8OR5biMMS3808UXf8LFw1h8rRRfkMVXvRSAjJxIAYCrFOG7MrzW+pn6kTilPrEsh2P6wvuZAAAAAElFTkSuQmCC","@class":"android.widget.Image","@package":"com.ss.android.ugc.aweme","@checkable":false,"@checked":false,"@clickable":false,"@enabled":true,"@focusable":false,"@focused":false,"@scrollable":false,"@long-clickable":false,"@selected":false,"@editable":false,"@bounds":"[942,1542][981,1578]","@screenBounds":"[0,0][0,0]"}]},{"@timestamp":"1717762278618","@index":4,"@text":"关闭提示：若您在30天内存在消费历史，关闭抖音月付可能会影响退款到账时效，请谨慎操作。抖音月付关闭后，将清除您所有的订单历史及还款记录，且后续二次开通额度将根据您的综合信息实时评定","@class":"android.view.View","@package":"com.ss.android.ugc.aweme","@checkable":false,"@checked":false,"@clickable":false,"@enabled":true,"@focusable":false,"@focused":false,"@scrollable":false,"@long-clickable":false,"@selected":false,"@editable":false,"@bounds":"[42,1701][1038,1968]","@screenBounds":"[0,0][0,0]"},{"@timestamp":"1717762278618","@index":5,"@text":"","@class":"android.view.View","@package":"com.ss.android.ugc.aweme","@checkable":false,"@checked":false,"@clickable":false,"@enabled":true,"@focusable":false,"@focused":false,"@scrollable":false,"@long-clickable":false,"@selected":false,"@editable":false,"@bounds":"[0,1944][1080,2192]","@screenBounds":"[0,0][0,0]","node":[{"@timestamp":"1717762278618","@index":0,"@text":"仍要关闭","@resource-id":"","@class":"android.view.View","@package":"com.ss.android.ugc.aweme","@checkable":false,"@checked":false,"@clickable":true,"@enabled":true,"@focusable":false,"@focused":false,"@scrollable":false,"@long-clickable":false,"@selected":false,"@editable":false,"@bounds":"[42,1977][528,2121]","@screenBounds":"[0,0][0,0]"},{"@timestamp":"1717762278618","@index":1,"@text":"先用用看","@resource-id":"","@class":"android.view.View","@package":"com.ss.android.ugc.aweme","@checkable":false,"@checked":false,"@clickable":true,"@enabled":true,"@focusable":false,"@focused":false,"@scrollable":false,"@long-clickable":false,"@selected":false,"@editable":false,"@bounds":"[552,1977][1038,2121]","@screenBounds":"[0,0][0,0]"},{"@timestamp":"1717762278618","@index":2,"@text":"更多人选择","@class":"android.view.View","@package":"com.ss.android.ugc.aweme","@checkable":false,"@checked":false,"@clickable":false,"@enabled":true,"@focusable":false,"@focused":false,"@scrollable":false,"@long-clickable":false,"@selected":false,"@editable":false,"@bounds":"[822,1932][1038,1998]","@screenBounds":"[0,0][0,0]"}]}]}}}}}}}}}}}}}}}}}