{"@timestamp":"1717768595351","@index":0,"@class":"android.widget.FrameLayout","@package":"com.android.settings","@checkable":false,"@checked":false,"@clickable":false,"@enabled":true,"@focusable":false,"@focused":false,"@scrollable":false,"@long-clickable":false,"@selected":false,"@editable":false,"@bounds":"[0,0][1080,2310]","@screenBounds":"[0,0][0,0]","node":{"@timestamp":"1717768595352","@index":0,"@class":"android.widget.LinearLayout","@package":"com.android.settings","@checkable":false,"@checked":false,"@clickable":false,"@enabled":true,"@focusable":false,"@focused":false,"@scrollable":false,"@long-clickable":false,"@selected":false,"@editable":false,"@bounds":"[0,0][1080,2192]","@screenBounds":"[0,0][0,0]","node":{"@timestamp":"1717768595352","@index":0,"@resource-id":"android:id\/content","@class":"android.widget.FrameLayout","@package":"com.android.settings","@checkable":false,"@checked":false,"@clickable":false,"@enabled":true,"@focusable":false,"@focused":false,"@scrollable":false,"@long-clickable":false,"@selected":false,"@editable":false,"@bounds":"[0,0][1080,2192]","@screenBounds":"[0,0][0,0]","node":{"@timestamp":"1717768595352","@index":0,"@resource-id":"com.android.settings:id\/drawer_layout","@class":"androidx.drawerlayout.widget.DrawerLayout","@package":"com.android.settings","@checkable":false,"@checked":false,"@clickable":false,"@enabled":true,"@focusable":false,"@focused":false,"@scrollable":false,"@long-clickable":false,"@selected":false,"@editable":false,"@bounds":"[0,0][1080,2192]","@screenBounds":"[0,0][0,0]","node":{"@timestamp":"1717768595352","@index":0,"@resource-id":"com.android.settings:id\/content_parent","@class":"android.widget.LinearLayout","@package":"com.android.settings","@checkable":false,"@checked":false,"@clickable":false,"@enabled":true,"@focusable":false,"@focused":false,"@scrollable":false,"@long-clickable":false,"@selected":false,"@editable":false,"@bounds":"[0,0][1080,2192]","@screenBounds":"[0,0][0,0]","node":{"@timestamp":"1717768595352","@index":0,"@resource-id":"com.android.settings:id\/content_frame","@class":"android.widget.FrameLayout","@package":"com.android.settings","@checkable":false,"@checked":false,"@clickable":false,"@enabled":true,"@focusable":false,"@focused":false,"@scrollable":false,"@long-clickable":false,"@selected":false,"@editable":false,"@bounds":"[0,117][1080,2192]","@screenBounds":"[0,0][0,0]","node":{"@timestamp":"1717768595352","@index":0,"@resource-id":"com.android.settings:id\/main_content","@class":"android.widget.FrameLayout","@package":"com.android.settings","@checkable":false,"@checked":false,"@clickable":false,"@enabled":true,"@focusable":false,"@focused":false,"@scrollable":false,"@long-clickable":false,"@selected":false,"@editable":false,"@bounds":"[0,117][1080,2192]","@screenBounds":"[0,0][0,0]","node":{"@timestamp":"1717768595352","@index":0,"@resource-id":"androidhwext:id\/coordinator_layout","@class":"android.view.ViewGroup","@package":"com.android.settings","@checkable":false,"@checked":false,"@clickable":false,"@enabled":true,"@focusable":false,"@focused":false,"@scrollable":false,"@long-clickable":false,"@selected":false,"@editable":false,"@bounds":"[0,117][1080,2192]","@screenBounds":"[0,0][0,0]","node":[{"@timestamp":"1717768595352","@index":0,"@resource-id":"androidhwext:id\/appbar_layout","@class":"android.widget.LinearLayout","@package":"com.android.settings","@checkable":false,"@checked":false,"@clickable":false,"@enabled":true,"@focusable":false,"@focused":false,"@scrollable":false,"@long-clickable":false,"@selected":false,"@editable":false,"@bounds":"[0,117][1080,285]","@screenBounds":"[0,0][0,0]","node":{"@timestamp":"1717768595352","@index":0,"@resource-id":"androidhwext:id\/collapsing_toolbar","@class":"android.widget.FrameLayout","@package":"com.android.settings","@content-desc":"设置","@checkable":false,"@checked":false,"@clickable":false,"@enabled":true,"@focusable":false,"@focused":false,"@scrollable":false,"@long-clickable":false,"@selected":false,"@editable":false,"@bounds":"[0,117][1080,285]","@screenBounds":"[0,0][0,0]"}},{"@timestamp":"1717768595353","@index":1,"@resource-id":"androidhwext:id\/content_layout","@class":"android.widget.FrameLayout","@package":"com.android.settings","@checkable":false,"@checked":false,"@clickable":false,"@enabled":true,"@focusable":false,"@focused":false,"@scrollable":false,"@long-clickable":false,"@selected":false,"@editable":false,"@bounds":"[0,285][1080,2192]","@screenBounds":"[0,0][0,0]","node":{"@timestamp":"1717768595353","@index":0,"@resource-id":"com.android.settings:id\/dashboard_root","@class":"android.widget.RelativeLayout","@package":"com.android.settings","@checkable":false,"@checked":false,"@clickable":false,"@enabled":true,"@focusable":false,"@focused":false,"@scrollable":false,"@long-clickable":false,"@selected":false,"@editable":false,"@bounds":"[0,285][1080,2192]","@screenBounds":"[0,0][0,0]","node":{"@timestamp":"1717768595353","@index":0,"@class":"android.widget.FrameLayout","@package":"com.android.settings","@checkable":false,"@checked":false,"@clickable":false,"@enabled":true,"@focusable":false,"@focused":false,"@scrollable":false,"@long-clickable":false,"@selected":false,"@editable":false,"@bounds":"[0,285][1080,2192]","@screenBounds":"[0,0][0,0]","node":{"@timestamp":"1717768595353","@index":0,"@resource-id":"android:id\/list_container","@class":"android.widget.RelativeLayout","@package":"com.android.settings","@checkable":false,"@checked":false,"@clickable":false,"@enabled":true,"@focusable":false,"@focused":false,"@scrollable":false,"@long-clickable":false,"@selected":false,"@editable":false,"@bounds":"[0,285][1080,2192]","@screenBounds":"[0,0][0,0]","node":{"@timestamp":"1717768595353","@index":0,"@resource-id":"com.android.settings:id\/dashboard_container","@class":"androidx.recyclerview.widget.RecyclerView","@package":"com.android.settings","@checkable":false,"@checked":false,"@clickable":false,"@enabled":true,"@focusable":true,"@focused":false,"@scrollable":true,"@long-clickable":false,"@selected":false,"@editable":false,"@bounds":"[0,285][1080,2192]","@screenBounds":"[0,0][0,0]","node":[{"@timestamp":"1717768595353","@index":0,"@class":"android.widget.LinearLayout","@package":"com.android.settings","@checkable":false,"@checked":false,"@clickable":true,"@enabled":true,"@focusable":true,"@focused":false,"@scrollable":false,"@long-clickable":false,"@selected":false,"@editable":false,"@bounds":"[0,285][1080,431]","@screenBounds":"[0,0][0,0]","node":{"@timestamp":"1717768595354","@index":0,"@resource-id":"com.android.settings:id\/card_area","@class":"android.widget.LinearLayout","@package":"com.android.settings","@checkable":false,"@checked":false,"@clickable":false,"@enabled":true,"@focusable":false,"@focused":false,"@scrollable":false,"@long-clickable":false,"@selected":false,"@editable":false,"@bounds":"[0,285][1080,431]","@screenBounds":"[0,0][0,0]","node":{"@timestamp":"1717768595354","@index":0,"@resource-id":"com.android.settings:id\/dashboard_tile","@class":"android.widget.LinearLayout","@package":"com.android.settings","@checkable":false,"@checked":false,"@clickable":false,"@enabled":true,"@focusable":false,"@focused":false,"@scrollable":false,"@long-clickable":false,"@selected":false,"@editable":false,"@bounds":"[0,285][1080,431]","@screenBounds":"[0,0][0,0]","node":[{"@timestamp":"1717768595354","@index":0,"@class":"android.widget.LinearLayout","@package":"com.android.settings","@checkable":false,"@checked":false,"@clickable":false,"@enabled":true,"@focusable":false,"@focused":false,"@scrollable":false,"@long-clickable":false,"@selected":false,"@editable":false,"@bounds":"[72,287][336,406]","@screenBounds":"[0,0][0,0]","node":{"@timestamp":"1717768595354","@index":0,"@text":"蓝牙","@resource-id":"android:id\/title","@class":"android.widget.TextView","@package":"com.android.settings","@checkable":false,"@checked":false,"@clickable":false,"@enabled":true,"@focusable":false,"@focused":false,"@scrollable":false,"@long-clickable":false,"@selected":false,"@editable":false,"@bounds":"[216,314][312,379]","@screenBounds":"[0,0][0,0]"}},{"@timestamp":"1717768595354","@index":1,"@class":"android.widget.RelativeLayout","@package":"com.android.settings","@checkable":false,"@checked":false,"@clickable":false,"@enabled":true,"@focusable":false,"@focused":false,"@scrollable":false,"@long-clickable":false,"@selected":false,"@editable":false,"@bounds":"[336,291][1008,402]","@screenBounds":"[0,0][0,0]","node":{"@timestamp":"1717768595354","@index":0,"@text":"已开启","@resource-id":"android:id\/summary","@class":"android.widget.TextView","@package":"com.android.settings","@checkable":false,"@checked":false,"@clickable":false,"@enabled":true,"@focusable":false,"@focused":false,"@scrollable":false,"@long-clickable":false,"@selected":false,"@editable":false,"@bounds":"[336,318][960,375]","@screenBounds":"[0,0][0,0]"}}]}}},{"@timestamp":"1717768595354","@index":1,"@class":"android.widget.LinearLayout","@package":"com.android.settings","@checkable":false,"@checked":false,"@clickable":true,"@enabled":true,"@focusable":true,"@focused":false,"@scrollable":false,"@long-clickable":false,"@selected":false,"@editable":false,"@bounds":"[0,431][1080,599]","@screenBounds":"[0,0][0,0]","node":{"@timestamp":"1717768595354","@index":0,"@resource-id":"com.android.settings:id\/card_area","@class":"android.widget.LinearLayout","@package":"com.android.settings","@checkable":false,"@checked":false,"@clickable":false,"@enabled":true,"@focusable":false,"@focused":false,"@scrollable":false,"@long-clickable":false,"@selected":false,"@editable":false,"@bounds":"[0,431][1080,599]","@screenBounds":"[0,0][0,0]","node":{"@timestamp":"1717768595354","@index":0,"@resource-id":"com.android.settings:id\/dashboard_tile","@class":"android.widget.LinearLayout","@package":"com.android.settings","@checkable":false,"@checked":false,"@clickable":false,"@enabled":true,"@focusable":false,"@focused":false,"@scrollable":false,"@long-clickable":false,"@selected":false,"@editable":false,"@bounds":"[0,431][1080,599]","@screenBounds":"[0,0][0,0]","node":{"@timestamp":"1717768595354","@index":0,"@text":"移动网络","@resource-id":"android:id\/title","@class":"android.widget.TextView","@package":"com.android.settings","@checkable":false,"@checked":false,"@clickable":false,"@enabled":true,"@focusable":false,"@focused":false,"@scrollable":false,"@long-clickable":false,"@selected":false,"@editable":false,"@bounds":"[216,482][936,547]","@screenBounds":"[0,0][0,0]"}}}},{"@timestamp":"1717768595354","@index":2,"@class":"android.widget.LinearLayout","@package":"com.android.settings","@checkable":false,"@checked":false,"@clickable":true,"@enabled":true,"@focusable":true,"@focused":false,"@scrollable":false,"@long-clickable":false,"@selected":false,"@editable":false,"@bounds":"[0,599][1080,767]","@screenBounds":"[0,0][0,0]","node":{"@timestamp":"1717768595354","@index":0,"@resource-id":"com.android.settings:id\/card_area","@class":"android.widget.LinearLayout","@package":"com.android.settings","@checkable":false,"@checked":false,"@clickable":false,"@enabled":true,"@focusable":false,"@focused":false,"@scrollable":false,"@long-clickable":false,"@selected":false,"@editable":false,"@bounds":"[0,599][1080,767]","@screenBounds":"[0,0][0,0]","node":{"@timestamp":"1717768595354","@index":0,"@resource-id":"com.android.settings:id\/dashboard_tile","@class":"android.widget.LinearLayout","@package":"com.android.settings","@checkable":false,"@checked":false,"@clickable":false,"@enabled":true,"@focusable":false,"@focused":false,"@scrollable":false,"@long-clickable":false,"@selected":false,"@editable":false,"@bounds":"[0,599][1080,767]","@screenBounds":"[0,0][0,0]","node":{"@timestamp":"1717768595354","@index":0,"@text":"超级终端","@resource-id":"android:id\/title","@class":"android.widget.TextView","@package":"com.android.settings","@checkable":false,"@checked":false,"@clickable":false,"@enabled":true,"@focusable":false,"@focused":false,"@scrollable":false,"@long-clickable":false,"@selected":false,"@editable":false,"@bounds":"[216,650][936,715]","@screenBounds":"[0,0][0,0]"}}}},{"@timestamp":"1717768595354","@index":3,"@class":"android.widget.LinearLayout","@package":"com.android.settings","@checkable":false,"@checked":false,"@clickable":true,"@enabled":true,"@focusable":true,"@focused":false,"@scrollable":false,"@long-clickable":false,"@selected":false,"@editable":false,"@bounds":"[0,767][1080,947]","@screenBounds":"[0,0][0,0]","node":{"@timestamp":"1717768595354","@index":0,"@resource-id":"com.android.settings:id\/card_area","@class":"android.widget.LinearLayout","@package":"com.android.settings","@checkable":false,"@checked":false,"@clickable":false,"@enabled":true,"@focusable":false,"@focused":false,"@scrollable":false,"@long-clickable":false,"@selected":false,"@editable":false,"@bounds":"[0,767][1080,947]","@screenBounds":"[0,0][0,0]","node":{"@timestamp":"1717768595354","@index":0,"@resource-id":"com.android.settings:id\/dashboard_tile","@class":"android.widget.LinearLayout","@package":"com.android.settings","@checkable":false,"@checked":false,"@clickable":false,"@enabled":true,"@focusable":false,"@focused":false,"@scrollable":false,"@long-clickable":false,"@selected":false,"@editable":false,"@bounds":"[0,767][1080,935]","@screenBounds":"[0,0][0,0]","node":{"@timestamp":"1717768595354","@index":0,"@text":"更多连接","@resource-id":"android:id\/title","@class":"android.widget.TextView","@package":"com.android.settings","@checkable":false,"@checked":false,"@clickable":false,"@enabled":true,"@focusable":false,"@focused":false,"@scrollable":false,"@long-clickable":false,"@selected":false,"@editable":false,"@bounds":"[216,818][936,883]","@screenBounds":"[0,0][0,0]"}}}},{"@timestamp":"1717768595354","@index":4,"@class":"android.widget.LinearLayout","@package":"com.android.settings","@checkable":false,"@checked":false,"@clickable":true,"@enabled":true,"@focusable":true,"@focused":false,"@scrollable":false,"@long-clickable":false,"@selected":false,"@editable":false,"@bounds":"[0,983][1080,1163]","@screenBounds":"[0,0][0,0]","node":{"@timestamp":"1717768595355","@index":0,"@resource-id":"com.android.settings:id\/card_area","@class":"android.widget.LinearLayout","@package":"com.android.settings","@checkable":false,"@checked":false,"@clickable":false,"@enabled":true,"@focusable":false,"@focused":false,"@scrollable":false,"@long-clickable":false,"@selected":false,"@editable":false,"@bounds":"[0,983][1080,1163]","@screenBounds":"[0,0][0,0]","node":{"@timestamp":"1717768595355","@index":0,"@resource-id":"com.android.settings:id\/dashboard_tile","@class":"android.widget.LinearLayout","@package":"com.android.settings","@checkable":false,"@checked":false,"@clickable":false,"@enabled":true,"@focusable":false,"@focused":false,"@scrollable":false,"@long-clickable":false,"@selected":false,"@editable":false,"@bounds":"[0,995][1080,1163]","@screenBounds":"[0,0][0,0]","node":{"@timestamp":"1717768595355","@index":0,"@text":"桌面和个性化","@resource-id":"android:id\/title","@class":"android.widget.TextView","@package":"com.android.settings","@checkable":false,"@checked":false,"@clickable":false,"@enabled":true,"@focusable":false,"@focused":false,"@scrollable":false,"@long-clickable":false,"@selected":false,"@editable":false,"@bounds":"[216,1046][936,1111]","@screenBounds":"[0,0][0,0]"}}}},{"@timestamp":"1717768595355","@index":5,"@class":"android.widget.LinearLayout","@package":"com.android.settings","@checkable":false,"@checked":false,"@clickable":true,"@enabled":true,"@focusable":true,"@focused":false,"@scrollable":false,"@long-clickable":false,"@selected":false,"@editable":false,"@bounds":"[0,1163][1080,1343]","@screenBounds":"[0,0][0,0]","node":{"@timestamp":"1717768595355","@index":0,"@resource-id":"com.android.settings:id\/card_area","@class":"android.widget.LinearLayout","@package":"com.android.settings","@checkable":false,"@checked":false,"@clickable":false,"@enabled":true,"@focusable":false,"@focused":false,"@scrollable":false,"@long-clickable":false,"@selected":false,"@editable":false,"@bounds":"[0,1163][1080,1343]","@screenBounds":"[0,0][0,0]","node":{"@timestamp":"1717768595355","@index":0,"@resource-id":"com.android.settings:id\/dashboard_tile","@class":"android.widget.LinearLayout","@package":"com.android.settings","@checkable":false,"@checked":false,"@clickable":false,"@enabled":true,"@focusable":false,"@focused":false,"@scrollable":false,"@long-clickable":false,"@selected":false,"@editable":false,"@bounds":"[0,1163][1080,1331]","@screenBounds":"[0,0][0,0]","node":{"@timestamp":"1717768595355","@index":0,"@text":"显示和亮度","@resource-id":"android:id\/title","@class":"android.widget.TextView","@package":"com.android.settings","@checkable":false,"@checked":false,"@clickable":false,"@enabled":true,"@focusable":false,"@focused":false,"@scrollable":false,"@long-clickable":false,"@selected":false,"@editable":false,"@bounds":"[216,1214][936,1279]","@screenBounds":"[0,0][0,0]"}}}},{"@timestamp":"1717768595355","@index":6,"@class":"android.widget.LinearLayout","@package":"com.android.settings","@checkable":false,"@checked":false,"@clickable":true,"@enabled":true,"@focusable":true,"@focused":false,"@scrollable":false,"@long-clickable":false,"@selected":false,"@editable":false,"@bounds":"[0,1379][1080,1559]","@screenBounds":"[0,0][0,0]","node":{"@timestamp":"1717768595355","@index":0,"@resource-id":"com.android.settings:id\/card_area","@class":"android.widget.LinearLayout","@package":"com.android.settings","@checkable":false,"@checked":false,"@clickable":false,"@enabled":true,"@focusable":false,"@focused":false,"@scrollable":false,"@long-clickable":false,"@selected":false,"@editable":false,"@bounds":"[0,1379][1080,1559]","@screenBounds":"[0,0][0,0]","node":{"@timestamp":"1717768595355","@index":0,"@resource-id":"com.android.settings:id\/dashboard_tile","@class":"android.widget.LinearLayout","@package":"com.android.settings","@checkable":false,"@checked":false,"@clickable":false,"@enabled":true,"@focusable":false,"@focused":false,"@scrollable":false,"@long-clickable":false,"@selected":false,"@editable":false,"@bounds":"[0,1391][1080,1559]","@screenBounds":"[0,0][0,0]","node":{"@timestamp":"1717768595355","@index":0,"@text":"声音和振动","@resource-id":"android:id\/title","@class":"android.widget.TextView","@package":"com.android.settings","@checkable":false,"@checked":false,"@clickable":false,"@enabled":true,"@focusable":false,"@focused":false,"@scrollable":false,"@long-clickable":false,"@selected":false,"@editable":false,"@bounds":"[216,1442][936,1507]","@screenBounds":"[0,0][0,0]"}}}},{"@timestamp":"1717768595355","@index":7,"@class":"android.widget.LinearLayout","@package":"com.android.settings","@checkable":false,"@checked":false,"@clickable":true,"@enabled":true,"@focusable":true,"@focused":false,"@scrollable":false,"@long-clickable":false,"@selected":false,"@editable":false,"@bounds":"[0,1559][1080,1739]","@screenBounds":"[0,0][0,0]","node":{"@timestamp":"1717768595355","@index":0,"@resource-id":"com.android.settings:id\/card_area","@class":"android.widget.LinearLayout","@package":"com.android.settings","@checkable":false,"@checked":false,"@clickable":false,"@enabled":true,"@focusable":false,"@focused":false,"@scrollable":false,"@long-clickable":false,"@selected":false,"@editable":false,"@bounds":"[0,1559][1080,1739]","@screenBounds":"[0,0][0,0]","node":{"@timestamp":"1717768595355","@index":0,"@resource-id":"com.android.settings:id\/dashboard_tile","@class":"android.widget.LinearLayout","@package":"com.android.settings","@checkable":false,"@checked":false,"@clickable":false,"@enabled":true,"@focusable":false,"@focused":false,"@scrollable":false,"@long-clickable":false,"@selected":false,"@editable":false,"@bounds":"[0,1559][1080,1727]","@screenBounds":"[0,0][0,0]","node":{"@timestamp":"1717768595355","@index":0,"@text":"通知和状态栏","@resource-id":"android:id\/title","@class":"android.widget.TextView","@package":"com.android.settings","@checkable":false,"@checked":false,"@clickable":false,"@enabled":true,"@focusable":false,"@focused":false,"@scrollable":false,"@long-clickable":false,"@selected":false,"@editable":false,"@bounds":"[216,1610][936,1675]","@screenBounds":"[0,0][0,0]"}}}},{"@timestamp":"1717768595355","@index":8,"@class":"android.widget.LinearLayout","@package":"com.android.settings","@checkable":false,"@checked":false,"@clickable":true,"@enabled":true,"@focusable":true,"@focused":false,"@scrollable":false,"@long-clickable":false,"@selected":false,"@editable":false,"@bounds":"[0,1775][1080,1955]","@screenBounds":"[0,0][0,0]","node":{"@timestamp":"1717768595355","@index":0,"@resource-id":"com.android.settings:id\/card_area","@class":"android.widget.LinearLayout","@package":"com.android.settings","@checkable":false,"@checked":false,"@clickable":false,"@enabled":true,"@focusable":false,"@focused":false,"@scrollable":false,"@long-clickable":false,"@selected":false,"@editable":false,"@bounds":"[0,1775][1080,1955]","@screenBounds":"[0,0][0,0]","node":{"@timestamp":"1717768595355","@index":0,"@resource-id":"com.android.settings:id\/dashboard_tile","@class":"android.widget.LinearLayout","@package":"com.android.settings","@checkable":false,"@checked":false,"@clickable":false,"@enabled":true,"@focusable":false,"@focused":false,"@scrollable":false,"@long-clickable":false,"@selected":false,"@editable":false,"@bounds":"[0,1787][1080,1955]","@screenBounds":"[0,0][0,0]","node":{"@timestamp":"1717768595355","@index":0,"@text":"生物识别和密码","@resource-id":"android:id\/title","@class":"android.widget.TextView","@package":"com.android.settings","@checkable":false,"@checked":false,"@clickable":false,"@enabled":true,"@focusable":false,"@focused":false,"@scrollable":false,"@long-clickable":false,"@selected":false,"@editable":false,"@bounds":"[216,1838][936,1903]","@screenBounds":"[0,0][0,0]"}}}},{"@timestamp":"1717768595356","@index":9,"@class":"android.widget.LinearLayout","@package":"com.android.settings","@checkable":false,"@checked":false,"@clickable":true,"@enabled":true,"@focusable":true,"@focused":false,"@scrollable":false,"@long-clickable":false,"@selected":false,"@editable":false,"@bounds":"[0,1955][1080,2123]","@screenBounds":"[0,0][0,0]","node":{"@timestamp":"1717768595356","@index":0,"@resource-id":"com.android.settings:id\/card_area","@class":"android.widget.LinearLayout","@package":"com.android.settings","@checkable":false,"@checked":false,"@clickable":false,"@enabled":true,"@focusable":false,"@focused":false,"@scrollable":false,"@long-clickable":false,"@selected":false,"@editable":false,"@bounds":"[0,1955][1080,2123]","@screenBounds":"[0,0][0,0]","node":{"@timestamp":"1717768595356","@index":0,"@resource-id":"com.android.settings:id\/dashboard_tile","@class":"android.widget.LinearLayout","@package":"com.android.settings","@checkable":false,"@checked":false,"@clickable":false,"@enabled":true,"@focusable":false,"@focused":false,"@scrollable":false,"@long-clickable":false,"@selected":false,"@editable":false,"@bounds":"[0,1955][1080,2123]","@screenBounds":"[0,0][0,0]","node":{"@timestamp":"1717768595356","@index":0,"@class":"android.widget.LinearLayout","@package":"com.android.settings","@checkable":false,"@checked":false,"@clickable":false,"@enabled":true,"@focusable":false,"@focused":false,"@scrollable":false,"@long-clickable":false,"@selected":false,"@editable":false,"@bounds":"[72,1979][960,2098]","@screenBounds":"[0,0][0,0]","node":{"@timestamp":"1717768595356","@index":0,"@text":"应用和服务","@resource-id":"android:id\/title","@class":"android.widget.TextView","@package":"com.android.settings","@checkable":false,"@checked":false,"@clickable":false,"@enabled":true,"@focusable":false,"@focused":false,"@scrollable":false,"@long-clickable":false,"@selected":false,"@editable":false,"@bounds":"[216,2006][456,2071]","@screenBounds":"[0,0][0,0]"}}}}},{"@timestamp":"1717768595356","@index":10,"@class":"android.widget.LinearLayout","@package":"com.android.settings","@checkable":false,"@checked":false,"@clickable":true,"@enabled":true,"@focusable":true,"@focused":false,"@scrollable":false,"@long-clickable":false,"@selected":false,"@editable":false,"@bounds":"[0,2123][1080,2192]","@screenBounds":"[0,0][0,0]","node":{"@timestamp":"1717768595356","@index":0,"@resource-id":"com.android.settings:id\/card_area","@class":"android.widget.LinearLayout","@package":"com.android.settings","@checkable":false,"@checked":false,"@clickable":false,"@enabled":true,"@focusable":false,"@focused":false,"@scrollable":false,"@long-clickable":false,"@selected":false,"@editable":false,"@bounds":"[0,2123][1080,2192]","@screenBounds":"[0,0][0,0]","node":{"@timestamp":"1717768595356","@index":0,"@resource-id":"com.android.settings:id\/dashboard_tile","@class":"android.widget.LinearLayout","@package":"com.android.settings","@checkable":false,"@checked":false,"@clickable":false,"@enabled":true,"@focusable":false,"@focused":false,"@scrollable":false,"@long-clickable":false,"@selected":false,"@editable":false,"@bounds":"[0,2123][1080,2192]","@screenBounds":"[0,0][0,0]","node":{"@timestamp":"1717768595356","@index":0,"@text":"电池","@resource-id":"android:id\/title","@class":"android.widget.TextView","@package":"com.android.settings","@checkable":false,"@checked":false,"@clickable":false,"@enabled":true,"@focusable":false,"@focused":false,"@scrollable":false,"@long-clickable":false,"@selected":false,"@editable":false,"@bounds":"[216,2174][936,2192]","@screenBounds":"[0,0][0,0]"}}}}]}}}}}]}}}}}}}}